mcp_server_zf/__init__.py
mcp_server_zf/server.py
mcp_server_zf-0.1.0.dist-info/METADATA
mcp_server_zf-0.1.0.dist-info/WHEEL
mcp_server_zf-0.1.0.dist-info/entry_points.txt
mcp_server_zf-0.1.0.dist-info/RECORD
