Metadata-Version: 2.4
Name: mcp-server-zf
Version: 0.1.0
Summary: test
Author-email: guozhifeng02 <guozhifeng02@meituan.com>
Requires-Python: >=3.13
Requires-Dist: mcp>=1.9.4
